{
  "value": {
    "title": "Test Page",
    "meta_description": "Test description",
    "text_content": "Main Content\n\n\nTest paragraph\n\n\nLink Text",
    "timestamp": "2025-02-23T12:28:13.913397",
    "links": [
      {
        "text": "Link Text",
        "url": "https://test.com",
        "title": "Test Link"
      }
    ],
    "images": [
      {
        "src": "test.jpg",
        "alt": "Test Image",
        "title": "Image Title"
      }
    ]
  },
  "timestamp": "2025-02-23T12:28:13.913805",
  "namespace": "default"
}